neogpt/.DS_Store
neogpt/__init__.py
neogpt/agents/.DS_Store
neogpt/agents/__init__.py
neogpt/agents/ml_engineer.py
neogpt/agents/qa_engineer.py
neogpt/builder.py
neogpt/builder_helpers/__init__.py
neogpt/builder_helpers/load_chats.py
neogpt/builder_helpers/load_code.py
neogpt/builder_helpers/load_docs.py
neogpt/builder_helpers/load_web.py
neogpt/callback_handler.py
neogpt/chat.py
neogpt/cli.py
neogpt/documents/1706.03762.pdf
neogpt/documents/2303.17580.pdf
neogpt/interpreter.py
neogpt/load_llm.py
neogpt/logs/builder.log
neogpt/logs/neogpt.log
neogpt/manager.py
neogpt/prompts/__init__.py
neogpt/prompts/agent_prompt.py
neogpt/prompts/hyper_prompt.py
neogpt/prompts/prompt.py
neogpt/retrievers/__init__.py
neogpt/retrievers/context_compress.py
neogpt/retrievers/hybrid.py
neogpt/retrievers/local.py
neogpt/retrievers/sql.py
neogpt/retrievers/stepback.py
neogpt/retrievers/web.py
neogpt/settings/__init__.py
neogpt/settings/config.py
neogpt/settings/export_config.py
neogpt/settings/settings.yaml
neogpt/ui.py
neogpt/utils/__init__.py
neogpt/utils/conversation_navigator.py
neogpt/utils/formatter.py
neogpt/utils/magic_commands.py
neogpt/utils/notify.py
neogpt/utils/read_file.py
neogpt/utils/system_info.py
neogpt/utils/user_info.py
neogpt/utils/writer_assistant.py
neogpt/vectorstore/__init__.py
neogpt/vectorstore/base.py
neogpt/vectorstore/chroma.py
neogpt/vectorstore/faiss.py
neogpt/vectorstore/pinecone.py
neogpt-0.1.0.dist-info/LICENSE
neogpt-0.1.0.dist-info/METADATA
neogpt-0.1.0.dist-info/WHEEL
neogpt-0.1.0.dist-info/entry_points.txt
neogpt-0.1.0.dist-info/RECORD
