Metadata-Version: 2.1
Name: neogpt
Version: 0.1.0
Summary: NeoGPT: Chat effortlessly with Documents, YouTube Videos,Code, and Social Media Chats. Your go-to for quick and smart interactions! 🤖💬
License: MIT
Author: Neokd
Requires-Python: >=3.8
Classifier: License :: OSI Approved :: MIT License
Classifier: Programming Language :: Python :: 3
Classifier: Programming Language :: Python :: 3.8
Classifier: Programming Language :: Python :: 3.9
Classifier: Programming Language :: Python :: 3.10
Classifier: Programming Language :: Python :: 3.11
Classifier: Programming Language :: Python :: 3.12
Requires-Dist: chromadb (>=0.4.23,<0.5.0)
Requires-Dist: duckduckgo-search (>=4.1.1,<5.0.0)
Requires-Dist: einops (>=0.7.0,<0.8.0)
Requires-Dist: faiss-cpu (>=1.7.4,<2.0.0)
Requires-Dist: google-api-python-client (==2.95.0)
Requires-Dist: html2text (>=2020.1.16,<2021.0.0)
Requires-Dist: instructorembedding (>=1.0.1,<2.0.0)
Requires-Dist: langchain (>=0.1.0,<0.2.0)
Requires-Dist: langchain-community (>=0.0.17,<0.0.18)
Requires-Dist: langchain-experimental (==0.0.42)
Requires-Dist: langchain-openai (>=0.0.2,<0.0.3)
Requires-Dist: llama-cpp-python (>=0.2.55,<0.3.0)
Requires-Dist: onnxruntime (>=1.14.0,<2.0.0)
Requires-Dist: openai (>=1.6.1,<2.0.0)
Requires-Dist: pdfminer-six (>=20231228,<20231229)
Requires-Dist: plyer (>=2.0.0,<3.0.0)
Requires-Dist: psutil (>=5.8.0,<6.0.0)
Requires-Dist: pyperclip (>=1.8.2,<2.0.0)
Requires-Dist: pytube (>=15.0.0,<16.0.0)
Requires-Dist: rank-bm25 (>=0.2.2,<0.3.0)
Requires-Dist: rich (>=13.7.0,<14.0.0)
Requires-Dist: sentence-transformers (>=2.2.2,<3.0.0)
Requires-Dist: streamlit (>=1.29.0,<2.0.0)
Requires-Dist: torch (>=2.2.2,<3.0.0)
Requires-Dist: unstructured (>=0.11.0,<0.12.0)
Requires-Dist: youtube-transcript-api (>=0.6.2,<0.7.0)
